[
null,
{"id":1,"animationId":0,"consumable":false,"damage":{"critical":false,"elementId":0,"formula":"0","type":0,"variance":20},"description":"里面有新生手册和其他的一些资料文件（游戏地图）","effects":[],"hitType":0,"iconIndex":274,"itypeId":1,"name":"新生大礼包","note":"","occasion":3,"price":233,"repeats":1,"scope":0,"speed":0,"successRate":100,"tpGain":0},
{"id":2,"animationId":0,"consumable":false,"damage":{"critical":false,"elementId":0,"formula":"0","type":0,"variance":20},"description":"看不懂上面的字，难道是某种小语种的书？","effects":[],"hitType":0,"iconIndex":189,"itypeId":2,"name":"奇怪的书","note":"","occasion":3,"price":0,"repeats":1,"scope":0,"speed":0,"successRate":100,"tpGain":0},
{"id":3,"animationId":0,"consumable":true,"damage":{"critical":false,"elementId":0,"formula":"0","type":0,"variance":20},"description":"不知道是用来打开什么的","effects":[],"hitType":0,"iconIndex":195,"itypeId":2,"name":"奇怪的钥匙","note":"","occasion":3,"price":0,"repeats":1,"scope":0,"speed":0,"successRate":100,"tpGain":0},
{"id":4,"animationId":0,"consumable":false,"damage":{"critical":false,"elementId":0,"formula":"0","type":0,"variance":20},"description":"爱国至上、振兴中华；严谨严格、求真务实；爱校如家、\n敬业奉献；开拓创新、艰苦奋斗","effects":[],"hitType":0,"iconIndex":314,"itypeId":2,"name":"竢实扬华奖章","note":"","occasion":3,"price":0,"repeats":1,"scope":0,"speed":0,"successRate":100,"tpGain":0},
{"id":5,"animationId":41,"consumable":true,"damage":{"critical":false,"elementId":0,"formula":"0","type":0,"variance":20},"description":"交大明信片，有神奇的效果哟~","effects":[{"code":11,"dataId":0,"value1":0.8,"value2":0},{"code":22,"dataId":1,"value1":1,"value2":0}],"hitType":0,"iconIndex":188,"itypeId":1,"name":"交大明信片","note":"","occasion":1,"price":99,"repeats":1,"scope":8,"speed":0,"successRate":100,"tpGain":0},
{"id":6,"animationId":42,"consumable":true,"damage":{"critical":false,"elementId":0,"formula":"0","type":0,"variance":20},"description":"好吃的不得了。","effects":[{"code":11,"dataId":0,"value1":0.5,"value2":200},{"code":22,"dataId":1,"value1":1,"value2":0}],"hitType":0,"iconIndex":258,"itypeId":1,"name":"狗粮","note":"","occasion":1,"price":1,"repeats":1,"scope":8,"speed":0,"successRate":100,"tpGain":0},
{"id":7,"animationId":80,"consumable":true,"damage":{"critical":false,"elementId":0,"formula":"0","type":0,"variance":20},"description":"骚年，你知道什么是无敌么。","effects":[{"code":21,"dataId":6,"value1":1,"value2":0},{"code":21,"dataId":4,"value1":1,"value2":0},{"code":32,"dataId":0,"value1":5,"value2":0},{"code":32,"dataId":2,"value1":5,"value2":0},{"code":32,"dataId":3,"value1":5,"value2":0},{"code":32,"dataId":6,"value1":5,"value2":0}],"hitType":0,"iconIndex":188,"itypeId":2,"name":"好人卡-女神特供版","note":"","occasion":1,"price":999999,"repeats":1,"scope":2,"speed":0,"successRate":100,"tpGain":0},
{"id":8,"animationId":0,"consumable":true,"damage":{"critical":false,"elementId":0,"formula":"0","type":0,"variance":20},"description":"","effects":[],"hitType":0,"iconIndex":0,"itypeId":1,"name":"","note":"","occasion":0,"price":0,"repeats":1,"scope":7,"speed":0,"successRate":100,"tpGain":0},
{"id":9,"animationId":0,"consumable":true,"damage":{"critical":false,"elementId":0,"formula":"0","type":0,"variance":20},"description":"","effects":[],"hitType":0,"iconIndex":0,"itypeId":1,"name":"","note":"","occasion":0,"price":0,"repeats":1,"scope":7,"speed":0,"successRate":100,"tpGain":0},
{"id":10,"animationId":0,"consumable":true,"damage":{"critical":false,"elementId":0,"formula":"0","type":0,"variance":20},"description":"","effects":[],"hitType":0,"iconIndex":0,"itypeId":1,"name":"","note":"","occasion":0,"price":0,"repeats":1,"scope":7,"speed":0,"successRate":100,"tpGain":0}
]